{
"kids":[
{
  "name":"עמית סייג",
  "gender":"m",
  "father-name":"אסי",
  "father-phone":"054-4411666",
  "mother-name":"דקלה",
  "mother-phone":"054-9997877",
  "image":"",
  "related-people":[
  {
    "name":"יסמין סייג",
    "number":"054-7411644"
  },
  {
    "name":"דוד סייג",
    "number":"054-4411600"
  }
  ]
},
{
  "name":"עמית בוולנגי",
  "gender":"m",
  "father-name":"דניאל",
  "father-phone":"054-4411666",
  "mother-name":"אסתר",
  "mother-phone":"054-9997877",
  "image":"",
  "related-people":[
  {
    "name":"סבתא",
    "number":"054-7411644"
  }
  ]
}
]

}
